pbi_prototype_query_translation/.gitignore
pbi_prototype_query_translation/Translation.pyi
pbi_prototype_query_translation/__init__.py
pbi_prototype_query_translation/__init__.pyi
pbi_prototype_query_translation/main.py
pbi_prototype_query_translation/libs/ASPlatformHost.dll
pbi_prototype_query_translation/libs/AngleSharp.dll
pbi_prototype_query_translation/libs/ApplicationInsights.config
pbi_prototype_query_translation/libs/AsyncFriendlyStackTrace.dll
pbi_prototype_query_translation/libs/Azure.Core.dll
pbi_prototype_query_translation/libs/Azure.Storage.Blobs.dll
pbi_prototype_query_translation/libs/Azure.Storage.Common.dll
pbi_prototype_query_translation/libs/CpuMathNative.dll
pbi_prototype_query_translation/libs/ExcelDataReader.dll
pbi_prototype_query_translation/libs/FlightRecorderTraceDef.xml
pbi_prototype_query_translation/libs/J2N.dll
pbi_prototype_query_translation/libs/Lucene.Net.Queries.dll
pbi_prototype_query_translation/libs/Lucene.Net.QueryParser.dll
pbi_prototype_query_translation/libs/Lucene.Net.Sandbox.dll
pbi_prototype_query_translation/libs/Lucene.Net.dll
pbi_prototype_query_translation/libs/Microsoft.AnalysisServices.AzureClient.dll
pbi_prototype_query_translation/libs/Microsoft.AnalysisServices.AzureClient.dll.manifest
pbi_prototype_query_translation/libs/Microsoft.AnalysisServices.DatasetSerializer.dll
pbi_prototype_query_translation/libs/Microsoft.AnalysisServices.DatasetSerializer.dll.manifest
pbi_prototype_query_translation/libs/Microsoft.AnalysisServices.Dax.ExtensionInterfaces.dll
pbi_prototype_query_translation/libs/Microsoft.AnalysisServices.Dax.Extensions.dll
pbi_prototype_query_translation/libs/Microsoft.AnalysisServices.ExecPlan.ExecPlanTypes.dll
pbi_prototype_query_translation/libs/Microsoft.AnalysisServices.ExecPlan.MBuilder.dll
pbi_prototype_query_translation/libs/Microsoft.AnalysisServices.MInterop.dll
pbi_prototype_query_translation/libs/Microsoft.AnalysisServices.MInterop.manifest
pbi_prototype_query_translation-1.1.6.dist-info/METADATA
pbi_prototype_query_translation-1.1.6.dist-info/WHEEL
pbi_prototype_query_translation-1.1.6.dist-info/RECORD
