Metadata-Version: 2.4
Name: pbi_prototype_query_translation
Version: 1.1.6
Summary: Converts PowerBI frontend Prototype Queries to DAX queries that can be understood by the SSAS backend
Project-URL: Homepage, https://github.com/douglassimonsen/pbi_prototype_query_translation
Project-URL: Documentation, https://douglassimonsen.github.io/pbi_prototype_query_translation/
Requires-Python: >=3.11.0
Requires-Dist: pythonnet>=3.0.5
Provides-Extra: dev
Requires-Dist: build>=1.2.2; extra == 'dev'
Requires-Dist: pre-commit>=3.8.0; extra == 'dev'
Provides-Extra: docs
Requires-Dist: mkdocs-material>=9.6.16; extra == 'docs'
Requires-Dist: mkdocs>=1.6.1; extra == 'docs'
Requires-Dist: mkdocstrings-python>=0.30.0; extra == 'docs'
